crypto_database.py
prices.db
templates/index.html
crypto_database-0.1.1.dist-info/entry_points.txt
crypto_database-0.1.1.dist-info/WHEEL
crypto_database-0.1.1.dist-info/METADATA
crypto_database-0.1.1.dist-info/RECORD
