Metadata-Version: 2.1
Name: crypto-database
Version: 0.1.1
Summary: An educational API (with database included) about cryptocurrencies
Author: Santiago Basulto
Author-email: santiago.basulto@gmail.com
Requires-Python: >=3.8,<4.0
Classifier: Programming Language :: Python :: 3
Classifier: Programming Language :: Python :: 3.8
Requires-Dist: flask (>=1.1.2,<2.0.0)
